sc_toolbox/__init__.py
sc_toolbox/plot/__init__.py
sc_toolbox/preprocessing/__init__.py
sc_toolbox/py.typed
sc_toolbox/tools/__init__.py
sc_toolbox/tools/markers/lung_particle_markers.txt
sc_toolbox/util/__init__.py
sc_toolbox-0.12.3.dist-info/LICENSE
sc_toolbox-0.12.3.dist-info/METADATA
sc_toolbox-0.12.3.dist-info/WHEEL
sc_toolbox-0.12.3.dist-info/entry_points.txt
sc_toolbox-0.12.3.dist-info/RECORD
