Metadata-Version: 2.1
Name: sc-toolbox
Version: 0.12.3
Summary: A collection of project templates and useful code snippets for single-cell data analysis with Scanpy.
Home-page: https://github.com/schillerlab/sc-toolbox
License: MIT
Author: Lukas Heumos
Author-email: lukas.heumos@posteo.net
Requires-Python: >=3.9.0,<4
Classifier: License :: OSI Approved :: MIT License
Classifier: Programming Language :: Python :: 3
Classifier: Programming Language :: Python :: 3.9
Classifier: Programming Language :: Python :: 3.10
Classifier: Programming Language :: Python :: 3.11
Requires-Dist: Jinja2 (>=2.11.3)
Requires-Dist: PyYAML (>=5.4.1)
Requires-Dist: adjustText (>=0.7.3)
Requires-Dist: cookiecutter (>=1.7.2)
Requires-Dist: matplotlib (>=3.4.1)
Requires-Dist: pandas (>=1.2.4)
Requires-Dist: pypi-latest (>=0.1.2)
Requires-Dist: questionary (>=1.9.0)
Requires-Dist: rich (>=10.1.0)
Requires-Dist: scanpy (>=1.7.2)
Requires-Dist: scikit-learn (>=0.24.1)
Requires-Dist: scipy (>=1.6.3)
Requires-Dist: seaborn (>=0.11.1)
Requires-Dist: typing-extensions (>=3.10.0)
Project-URL: Documentation, https://sc-toolbox.readthedocs.io
Project-URL: Repository, https://github.com/schillerlab/sc-toolbox
